revenium_mcp-0.2.1.dist-info/licenses/LICENSE
revenium_mcp_server/__init__.py
revenium_mcp_server/__main__.py
revenium_mcp_server/analytics_parameters.py
revenium_mcp_server/analytics_registry.py
revenium_mcp_server/api_field_mapper.py
revenium_mcp_server/auth.py
revenium_mcp_server/auto_discovery.py
revenium_mcp_server/client.py
revenium_mcp_server/config_cache.py
revenium_mcp_server/config_store.py
revenium_mcp_server/crash_handler.py
revenium_mcp_server/date_parser.py
revenium_mcp_server/enhanced_server.py
revenium_mcp_server/error_handlers.py
revenium_mcp_server/exceptions.py
revenium_mcp_server/intelligent_clarification_engine.py
revenium_mcp_server/json_schema_validator.py
revenium_mcp_server/logging_config.py
revenium_mcp_server/models.py
revenium_mcp_server/monitoring.py
revenium_mcp_server/naming_audit.py
revenium_mcp_server/naming_standards.py
revenium_mcp_server/nlp_processor.py
revenium_mcp_server/pagination.py
revenium_mcp_server/product_error_handler.py
revenium_mcp_server/product_schema_enhanced.py
revenium_mcp_server/product_templates.py
revenium_mcp_server/product_validation_engine.py
revenium_mcp_server/product_validators.py
revenium_mcp_server/schema_discovery.py
revenium_mcp_server/shared_parameters.py
revenium_mcp_server/smart_defaults.py
revenium_mcp_server/smart_defaults_integration.py
revenium_mcp_server/standard_errors.py
revenium_mcp_server/tools.py
revenium_mcp_server/validation_integration.py
revenium_mcp_server/validators.py
revenium_mcp_server/version.py
revenium_mcp_server/workflow_engine.py
revenium_mcp_server/agent_friendly/__init__.py
revenium_mcp_server/agent_friendly/base_implementations.py
revenium_mcp_server/agent_friendly/error_handling.py
revenium_mcp_server/agent_friendly/error_library.py
revenium_mcp_server/agent_friendly/interfaces.py
revenium_mcp_server/agent_friendly/response_formatting.py
revenium_mcp_server/agent_friendly/standard_formatter.py
revenium_mcp_server/agent_friendly/unified_error_handler.py
revenium_mcp_server/ai_routing/__init__.py
revenium_mcp-0.2.1.dist-info/METADATA
revenium_mcp-0.2.1.dist-info/WHEEL
revenium_mcp-0.2.1.dist-info/entry_points.txt
revenium_mcp-0.2.1.dist-info/top_level.txt
revenium_mcp-0.2.1.dist-info/RECORD
