Metadata-Version: 2.4
Name: revenium-mcp
Version: 0.2.1
Summary: Model Context Protocol (MCP) server for Revenium API monitoring, analytics, and AI spending management
Author-email: Jason Cumberland <jason@revenium.io>
Maintainer-email: Jason Cumberland <jason@revenium.io>
License-Expression: MIT
Project-URL: Homepage, https://github.com/revenium/revenium-mcp
Project-URL: Documentation, https://github.com/revenium/revenium-mcp#readme
Project-URL: Repository, https://github.com/revenium/revenium-mcp
Project-URL: Bug Tracker, https://github.com/revenium/revenium-mcp/issues
Keywords: mcp,revenium,api,ai,assistant,cli,server,model-context-protocol,anthropic,claude
Classifier: Development Status :: 3 - Alpha
Classifier: Intended Audience :: Developers
Classifier: Operating System :: OS Independent
Classifier: Programming Language :: Python :: 3
Classifier: Programming Language :: Python :: 3.11
Classifier: Programming Language :: Python :: 3.12
Classifier: Topic :: Software Development :: Libraries :: Python Modules
Classifier: Topic :: Internet :: WWW/HTTP :: HTTP Servers
Classifier: Topic :: Scientific/Engineering :: Artificial Intelligence
Classifier: Framework :: AsyncIO
Classifier: Environment :: Console
Classifier: Topic :: Utilities
Classifier: Typing :: Typed
Requires-Python: >=3.11
License-File: LICENSE
Requires-Dist: fastmcp>=0.1.0
Requires-Dist: httpx>=0.25.0
Requires-Dist: pydantic>=2.0.0
Requires-Dist: loguru>=0.7.0
Requires-Dist: structlog>=23.0.0
Requires-Dist: python-dotenv>=1.0.0
Requires-Dist: openai>=1.0.0
Requires-Dist: revenium-middleware-openai>=0.4.6
Requires-Dist: matplotlib>=3.7.0
Requires-Dist: numpy>=1.24.0
Requires-Dist: aiofiles>=23.0.0
Requires-Dist: diskcache>=5.6.0
Provides-Extra: dev
Requires-Dist: pytest>=7.0.0; extra == "dev"
Requires-Dist: pytest-cov>=4.0.0; extra == "dev"
Requires-Dist: pytest-asyncio>=0.21.0; extra == "dev"
Requires-Dist: pytest-mock>=3.10.0; extra == "dev"
Requires-Dist: black>=23.0.0; extra == "dev"
Requires-Dist: isort>=5.12.0; extra == "dev"
Requires-Dist: flake8>=6.0.0; extra == "dev"
Requires-Dist: mypy>=1.0.0; extra == "dev"
Requires-Dist: pre-commit>=3.0.0; extra == "dev"
Provides-Extra: test
Requires-Dist: pytest>=7.0.0; extra == "test"
Requires-Dist: pytest-cov>=4.0.0; extra == "test"
Requires-Dist: pytest-asyncio>=0.21.0; extra == "test"
Requires-Dist: pytest-mock>=3.10.0; extra == "test"
Requires-Dist: requests-mock>=1.10.0; extra == "test"
Dynamic: license-file
